{
	"description": "This is a single import.",
	"type": "type",
	"id": "import",
	"properties": {
		"name": {
			"description": "The prefix used by the package. If omitted, we use the last part of the package URL.",
			"type": "property",
			"optional": true,
			"item": {
				"type": "@string"
			}
		},
		"package": {
			"description": "The package path.",
			"type": "property",
			"item": {
				"type": "@string"
			}
		}
	},
	"rule": {
		"description": "Restriction rules for import",
		"type": "type",
		"id": "@import",
		"is": ["rule"]
	}
}